[
  {
    "html": [
      {
        "id": 1,
        "instructor": "Osama Elzero",
        "playListId": "PLDoPjvoNmBAxW8oSxDXmo3gFtVAV1_yHT",
        "advantages": "Provides clear and straightforward explanations, covering HTML fundamentals in-depth with practical examples. Known for high-quality Arabic content in web development.",
        "hours": 3,
        "image": "https://images.pexels.com/photos/546819/pexels-photo-546819.jpeg?auto=compress&cs=tinysrgb&w=1260&h=750&dpr=1",
        "lang": "HTML"
      },
      {
        "id": 2,
        "instructor": "Mohamed Khaled",
        "playListId": "PLbR7G8Z0DfxL8_NFOV8z8TOh6V_cCPO0H",
        "advantages": "Covers HTML5 in detail, including semantic elements, forms, and multimedia. Offers practical projects to reinforce learning.",
        "hours": 4,
        "image": "https://images.pexels.com/photos/577585/pexels-photo-577585.jpeg?auto=compress&cs=tinysrgb&w=600&lazy=load",
        "lang": "HTML"
      },
      {
        "id": 3,
        "instructor": "Abdelrahman Ahmed",
        "playListId": "PL8D2gA2R3sh5HfWFR4e0wXZCDcX3F93cv",
        "advantages": "Explains HTML concepts with a focus on real-world applications, making it easier for beginners to understand.",
        "hours": 5,
        "image": "https://images.pexels.com/photos/159299/graphic-design-studio-tracfone-programming-html-159299.jpeg?auto=compress&cs=tinysrgb&w=600&lazy=load",
        "lang": "HTML"
      },
      {
        "id": 4,
        "instructor": "Mohamed Saad",
        "playListId": "PL8fV9kWLTgwq4H1ZkRau9doC2k5Qf5B96",
        "advantages": "Focuses on practical HTML projects that allow students to apply what they've learned effectively.",
        "hours": 5,
        "image": "https://images.pexels.com/photos/6424590/pexels-photo-6424590.jpeg?auto=compress&cs=tinysrgb&w=600&lazy=load",
        "lang": "HTML"
      },
      {
        "id": 5,
        "instructor": "Ahmed Elzahrani",
        "playListId": "PL5w9U-3PhzTLHnbB1Z8vxRtVjRlKq3Eqh",
        "advantages": "Emphasizes hands-on learning and real-world applications of HTML.",
        "hours": 6,
        "image": "https://images.pexels.com/photos/633409/pexels-photo-633409.jpeg?auto=compress&cs=tinysrgb&w=600",
        "lang": "HTML"
      },
      {
        "id": 6,
        "instructor": "Yasser Elsharif",
        "playListId": "PLM8AW8uOKW1MO8r4W9LPZLeBnpv8wq5w7",
        "advantages": "Provides comprehensive coverage of HTML basics and advanced topics with examples.",
        "hours": 4,
        "image": "https://images.pexels.com/photos/234527/pexels-photo-234527.jpeg?auto=compress&cs=tinysrgb&w=600",
        "lang": "HTML"
      },
      {
        "id": 7,
        "instructor": "Omar Abdallah",
        "playListId": "PL4BCaNAlL1V3HoBiyHYKbeJ8sOVc4CEdr",
        "advantages": "Focuses on building responsive websites using HTML.",
        "hours": 5,
        "image": "https://images.pexels.com/photos/1779487/pexels-photo-1779487.jpeg?auto=compress&cs=tinysrgb&w=600",
        "lang": "HTML"
      },
      {
        "id": 8,
        "instructor": "Ali Mohammed",
        "playListId": "PL4QH12EUlV8snZ0QFYTX-3HDF_qtJsmn5",
        "advantages": "Covers practical examples of HTML in web development projects.",
        "hours": 4,
        "image": "https://i.ytimg.com/vi/vOUAdYta71A/hqdefault.jpg",
        "lang": "HTML"
      },
      {
        "id": 9,
        "instructor": "Hassan Farouk",
        "playListId": "PL4DcOtj2bNeNFybs5WvlUwXz75DLa7ZZ7",
        "advantages": "Incorporates projects that encourage students to apply HTML skills in real scenarios.",
        "hours": 6,
        "image": "https://i.ytimg.com/vi/64pCpPE7RzA/hqdefault.jpg",
        "lang": "HTML"
      },
      {
        "id": 10,
        "instructor": "Fouad Nagy",
        "playListId": "PL4wIFmUbwvnSO4hU6S_OoGrvLi7iNso5u",
        "advantages": "Engages students through interactive examples and quizzes in HTML.",
        "hours": 5,
        "image": "https://i.ytimg.com/vi/3mr5kJSRew0/hqdefault.jpg",
        "lang": "HTML"
      }
    ]
  }
]
